mailman_telegram_webhook/__init__.py
mailman_telegram_webhook/mailman-telegram-webhook.cfg
mailman_telegram_webhook-0.8.0.dist-info/LICENSE
mailman_telegram_webhook-0.8.0.dist-info/WHEEL
mailman_telegram_webhook-0.8.0.dist-info/METADATA
mailman_telegram_webhook-0.8.0.dist-info/RECORD
