Metadata-Version: 2.1
Name: mailman-telegram-webhook
Version: 0.8.0
Summary: A small archiver sending message to telegram chats.
Home-page: https://github.com/nanoy42/mailman-telegram-webhook
License: GPLv3
Keywords: mailman,telegram,webhook
Author: Yoann Piétri
Author-email: me@nanoy.fr
Requires-Python: >=3.7,<4
Classifier: License :: Other/Proprietary License
Classifier: Programming Language :: Python :: 3
Classifier: Programming Language :: Python :: 3.7
Classifier: Programming Language :: Python :: 3.8
Classifier: Programming Language :: Python :: 3.9
Classifier: Programming Language :: Python :: 3.10
Classifier: Programming Language :: Python :: 3.11
Requires-Dist: python-telegram-bot (>=13.15,<14.0)
Project-URL: Repository, https://github.com/nanoy42/mailman-telegram-webhook
